logblocks/__init__.py
logblocks/logblocks.py
licenseware_logblocks-0.3.0.dist-info/METADATA
licenseware_logblocks-0.3.0.dist-info/WHEEL
licenseware_logblocks-0.3.0.dist-info/entry_points.txt
licenseware_logblocks-0.3.0.dist-info/top_level.txt
licenseware_logblocks-0.3.0.dist-info/RECORD
