Metadata-Version: 2.1
Name: licenseware-logblocks
Version: 0.3.0
Summary: Post formatted log messages to slack, mentioning users when error ocurrs
Home-page: https://github.com/licenseware/licenseware-logblocks
Author: Licenseware
Author-email: contact@licenseware.com
Requires-Dist: slack-sdk
Requires-Dist: pytest
